pyinstallersubprocess/LICENSE
pyinstallersubprocess/README.MD
pyinstallersubprocess/__init__.py
pyinstallersubprocess/requirements.txt
pyinstallersubprocess/thirdparty.json
pyinstallersubprocess-0.10.dist-info/LICENSE.rst
pyinstallersubprocess-0.10.dist-info/METADATA
pyinstallersubprocess-0.10.dist-info/WHEEL
pyinstallersubprocess-0.10.dist-info/top_level.txt
pyinstallersubprocess-0.10.dist-info/RECORD
